drf_queryfields/__init__.py
drf_queryfields/mixins.py
djangorestframework_queryfields-1.1.0.dist-info/LICENSE
djangorestframework_queryfields-1.1.0.dist-info/METADATA
djangorestframework_queryfields-1.1.0.dist-info/WHEEL
djangorestframework_queryfields-1.1.0.dist-info/top_level.txt
djangorestframework_queryfields-1.1.0.dist-info/RECORD
