Metadata-Version: 2.1
Name: djangorestframework-queryfields
Version: 1.1.0
Summary: Serialize a partial subset of fields in the API
Home-page: https://github.com/wimglenn/djangorestframework-queryfields
Author: Wim Glenn
Author-email: hey@wimglenn.com
License: MIT
Classifier: Programming Language :: Python :: 2
Classifier: Programming Language :: Python :: 3
Classifier: License :: OSI Approved :: MIT License
Classifier: Topic :: Software Development :: Libraries
Classifier: Intended Audience :: Developers
Classifier: Framework :: Django
License-File: LICENSE
Provides-Extra: dev
Requires-Dist: pytest; extra == "dev"
Requires-Dist: pytest-cov; extra == "dev"
Requires-Dist: pytest-django; extra == "dev"
Requires-Dist: coveralls; extra == "dev"
Requires-Dist: django; extra == "dev"
Requires-Dist: djangorestframework; extra == "dev"
Requires-Dist: mock_django; extra == "dev"
Requires-Dist: setuptools; extra == "dev"
Requires-Dist: wheel; extra == "dev"
Requires-Dist: pytz; extra == "dev"
